phidelity/anonymizer.py
phidelity/cli.py
phidelity/sanitizer.py
phidelity-0.2.2.dist-info/licenses/LICENSE
phidelity-0.2.2.dist-info/METADATA
phidelity-0.2.2.dist-info/WHEEL
phidelity-0.2.2.dist-info/top_level.txt
phidelity-0.2.2.dist-info/RECORD
