Metadata-Version: 2.4
Name: PHIdelity
Version: 0.2.2
Summary: The tool extracts PHI into a structured CSV file and saves the anonymized note as a text file, making it ideal for healthcare professionals, researchers, and developers handling sensitive medical data.
Author-email: Udbhav Ram <udbhavram41@gmail.com>
License-Expression: MIT
Project-URL: Homepage, https://github.com/udiram/PHIdelity
Project-URL: Issues, https://github.com/udiram/PHIdelity/issues
Classifier: Programming Language :: Python :: 3
Classifier: Operating System :: OS Independent
Requires-Python: >=3.9
License-File: LICENSE
Dynamic: license-file
